botman/__init__.py
botman/bot.py
botman/cli.py
botman/errors.py
botman-0.0.14.dist-info/DESCRIPTION.rst
botman-0.0.14.dist-info/METADATA
botman-0.0.14.dist-info/RECORD
botman-0.0.14.dist-info/WHEEL
botman-0.0.14.dist-info/entry_points.txt
botman-0.0.14.dist-info/metadata.json
botman-0.0.14.dist-info/top_level.txt
