Metadata-Version: 2.0
Name: botman
Version: 0.0.14
Summary: A Discord chat bot
Home-page: https://github.com/durandj/botman
Author: James Durand
Author-email: james.durand@alumni.msoe.edu
License: MIT license
Keywords: botman
Platform: UNKNOWN
Classifier: Development Status :: 2 - Pre-Alpha
Classifier: Intended Audience :: Developers
Classifier: License :: OSI Approved :: MIT License
Classifier: Natural Language :: English
Classifier: Programming Language :: Python :: 3.4
Classifier: Programming Language :: Python :: 3.5
Classifier: Programming Language :: Python :: 3.6
Requires-Dist: Click (>=6.0)
Requires-Dist: discord.py (>=0.16.5)
Requires-Dist: tabulate (==0.7.7)
